vidimera/__init__.py
vidimera/assertions.py
vidimera/behaviour.py
vidimera/missing_behaviour.py
vidimera-0.3.1.dist-info/LICENSE
vidimera-0.3.1.dist-info/METADATA
vidimera-0.3.1.dist-info/WHEEL
vidimera-0.3.1.dist-info/top_level.txt
vidimera-0.3.1.dist-info/RECORD
