Metadata-Version: 2.1
Name: vidimera
Version: 0.3.1
Summary: Python signature and behaviour checker inspired by Elixir.
Home-page: https://github.com/DevL/vidimera
Author: Lennart Fridén
Author-email: lennart@devl.se
License: MIT
Project-URL: Bug Reports, https://github.com/DevL/vidimera/issues
Project-URL: Source, https://github.com/DevL/vidimera
Keywords: [signature,behaviour]
Classifier: Development Status :: 3 - Alpha
Classifier: License :: OSI Approved :: MIT License
Classifier: Programming Language :: Python :: 3
Classifier: Programming Language :: Python :: 3.9
Classifier: Programming Language :: Python :: 3.10
Classifier: Programming Language :: Python :: 3.11
Classifier: Programming Language :: Python :: 3.12
Classifier: Programming Language :: Python :: 3.13
Classifier: Topic :: Software Development :: Libraries
License-File: LICENSE
